jsonmodeler/__init__.py
jsonmodeler/json_modeler.py
jsonmodeler/json_parser.py
jsonmodeler/languages/__init__.py
jsonmodeler/languages/base.py
jsonmodeler/languages/cpp.py
jsonmodeler/languages/csharp.py
jsonmodeler/languages/dart.py
jsonmodeler/languages/go.py
jsonmodeler/languages/java.py
jsonmodeler/languages/js.py
jsonmodeler/languages/kotlin.py
jsonmodeler/languages/objc.py
jsonmodeler/languages/php.py
jsonmodeler/languages/python.py
jsonmodeler/languages/swift.py
jsonmodeler/languages/ts.py
scripts/__init__.py
scripts/convert.py
tests/__init__.py
tests/test_json_parser.py
tests/test_model_generator.py
jsonmodeler-0.2.2.dist-info/LICENSE
jsonmodeler-0.2.2.dist-info/METADATA
jsonmodeler-0.2.2.dist-info/WHEEL
jsonmodeler-0.2.2.dist-info/entry_points.txt
jsonmodeler-0.2.2.dist-info/top_level.txt
jsonmodeler-0.2.2.dist-info/RECORD
